{
  "constants": {
    "SAMPLE_SIZE_SECONDS": 0.5,
    "FM_FREQUENCIES": [
      0,
      0.2,
      0.5,
      1,
      2,
      3,
      4,
      5,
      6,
      7,
      8,
      9,
      10,
      11,
      12,
      13,
      14,
      15
    ],
    "FM_SHORT_DURATION": [
      1,
      1,
      0.97,
      0.94,
      0.91,
      0.88,
      0.84,
      0.8,
      0.75,
      0.7,
      0.6,
      0.52,
      0.45,
      0.41,
      0.37,
      0.34,
      0.31,
      0.28
    ],
    "FM_MODERATE_DURATION": [
      0.95,
      0.95,
      0.92,
      0.88,
      0.84,
      0.79,
      0.72,
      0.6,
      0.5,
      0.42,
      0.35,
      0.3,
      0.26,
      0.23,
      0.21,
      0,
      0,
      0
    ],
    "FM_LONG_DURATION": [
      0.85,
      0.85,
      0.81,
      0.75,
      0.65,
      0.55,
      0.45,
      0.35,
      0.27,
      0.22,
      0.18,
      0.15,
      0.13,
      0,
      0,
      0,
      0,
      0
    ],
    "FM_SHORT_DURATION_VERTICAL_CUTOFF": 13,
    "FM_MODERATE_DURATION_VERTICAL_CUTOFF": 10,
    "FM_LONG_DURATION_VERTICAL_CUTOFF": 8,
    "black": {
      "Color": "rgba(15, 15, 30, 0.9)"
    },
    "light_green": {
      "Color": "rgba(109, 208, 163, 1.0)"
    },
    "green": {
      "Color": "rgba(20, 210, 184, 1.0)"
    },
    "orange": {
      "Color": "rgba(234, 130, 130, 1.0)"
    },
    "red": {
      "Color": "rgba(184, 15, 10, 1.0)"
    },
    "unsafe": {
      "TranslateText": "niosh.score.unsafe",
      "ShortText": "Unsafe",
      "Color": "rgba(184, 15, 10, 1.0)"
    },
    "acceptable": {
      "TranslateText": "niosh.score.good",
      "ShortText": "Good",
      "Color": "rgba(109, 208, 163, 1.0)"
    },
    "low": {
      "TranslateText": "niosh.score.fair",
      "ShortText": "Fair",
      "Color": "rgba(234, 130, 130, 1.0)"
    },
    "medium": {
      "TranslateText": "niosh.score.poor",
      "ShortText": "Poor",
      "Color": "rgba(184, 15, 10, 1.0)"
    }
  },
  "ComponentValues": {
    "li": {
      "[None, 0]": {
        "Text": "Unsafe lift at all weights",
        "TranslateText": "niosh.score.unsafe",
        "ShortText": "Unsafe",
        "Color": "rgba(184, 15, 10, 1.0)",
        "Warning": null
      },
      "[0, 1.5]": {
        "Text": "Safe weight to lift",
        "TranslateText": "niosh.score.good",
        "ShortText": "Good",
        "Color": "rgba(109, 208, 163, 1.0)",
        "Warning": null
      },
      "[1.5, 2.5]": {
        "Text": "Weight moderately heavy",
        "TranslateText": "niosh.score.fair",
        "ShortText": "Fair",
        "Color": "rgba(234, 130, 130, 1.0)",
        "Warning": "Object heavy"
      },
      "[2.5, 10.0]": {
        "Text": "Weight heavy for given task",
        "TranslateText": "niosh.score.poor",
        "ShortText": "Poor",
        "Color": "rgba(184, 15, 10, 1.0)",
        "Warning": "Object far too heavy"
      },
      "[10.0, None]": {
        "Text": "Weight heavy for given task",
        "TranslateText": "niosh.score.poor",
        "ShortText": "Poor",
        "Color": "rgba(184, 15, 10, 1.0)",
        "Warning": "Object far too heavy"
      }
    },
    "hm": {
      "[0, .4]": {
        "TranslateText": "niosh.score.poor",
        "ShortText": "Poor",
        "Color": "rgba(184, 15, 10, 1.0)",
        "Warning": "Object too far away horizontally"
      },
      "[.4, .6]": {
        "TranslateText": "niosh.score.fair",
        "ShortText": "Fair",
        "Color": "rgba(234, 130, 130, 1.0)",
        "Warning": "Object too far away horizontally"
      },
      "[.6, None]": {
        "TranslateText": "niosh.score.good",
        "ShortText": "Good",
        "Color": "rgba(109, 208, 163, 1.0)",
        "Warning": null
      }
    },
    "vm": {
      "[0, .8]": {
        "TranslateText": "niosh.score.poor",
        "ShortText": "Poor",
        "Color": "rgba(184, 15, 10, 1.0)",
        "Warning": "Object begins too far away vertically"
      },
      "[.8, .9]": {
        "TranslateText": "niosh.score.fair",
        "ShortText": "Fair",
        "Color": "rgba(234, 130, 130, 1.0)",
        "Warning": null
      },
      "[.9, None]": {
        "TranslateText": "niosh.score.good",
        "ShortText": "Good",
        "Color": "rgba(109, 208, 163, 1.0)",
        "Warning": null
      }
    },
    "dm": {
      "[0, .9]": {
        "TranslateText": "niosh.score.poor",
        "ShortText": "Poor",
        "Color": "rgba(184, 15, 10, 1.0)",
        "Warning": "Object travels too far"
      },
      "[.9, .95]": {
        "TranslateText": "niosh.score.fair",
        "ShortText": "Fair",
        "Color": "rgba(234, 130, 130, 1.0)",
        "Warning": null
      },
      "[.95, None]": {
        "TranslateText": "niosh.score.good",
        "ShortText": "Good",
        "Color": "rgba(109, 208, 163, 1.0)",
        "Warning": null
      }
    },
    "am": {
      "[0, .7]": {
        "TranslateText": "niosh.score.poor",
        "ShortText": "Poor",
        "Color": "rgba(184, 15, 10, 1.0)",
        "Warning": "Person twists too much"
      },
      "[.7, .9]": {
        "TranslateText": "niosh.score.fair",
        "ShortText": "Fair",
        "Color": "rgba(234, 130, 130, 1.0)",
        "Warning": null
      },
      "[.9, None]": {
        "TranslateText": "niosh.score.good",
        "ShortText": "Good",
        "Color": "rgba(109, 208, 163, 1.0)",
        "Warning": null
      }
    },
    "fm": {
      "[0, .45]": {
        "TranslateText": "niosh.score.poor",
        "ShortText": "Poor",
        "Color": "rgba(184, 15, 10, 1.0)",
        "Warning": "Person twists too much"
      },
      "[.45, .8]": {
        "TranslateText": "niosh.score.fair",
        "ShortText": "Fair",
        "Color": "rgba(234, 130, 130, 1.0)",
        "Warning": null
      },
      "[.8, None]": {
        "TranslateText": "niosh.score.good",
        "ShortText": "Good",
        "Color": "rgba(109, 208, 163, 1.0)",
        "Warning": null
      }
    }
  },
  "CouplingStatus": {
    "GOOD": {
      "Number": 0,
      "Text": "Good"
    },
    "FAIR": {
      "Number": 1,
      "Text": "Fair"
    },
    "POOR": {
      "Number": 2,
      "Text": "Poor"
    }
  },
  "DurationStatus": {
    "SHORT": {
      "Number": 0,
      "Text": "Short (1 hour)"
    },
    "MODERATE": {
      "Number": 1,
      "Text": "Moderate (1 - 2 hours)"
    },
    "LONG": {
      "Number": 2,
      "Text": "Long (2 - 8 hours)"
    }
  },
  "HeightConstantsStandard": {
    "LESS_FOUR": 0,
    "FOUR_TO_FOUR_HALF": 1,
    "FOUR_HALF_TO_FIVE": 2,
    "FIVE_TO_FIVE_HALF": 3,
    "FIVE_HALF_TO_SIX": 4,
    "SIX_TO_SIX_HALF": 5,
    "SIX_HALF_PLUS": 6
  },
  "Units": {
    "STANDARD": 0,
    "METRIC": 1
  }
}
